matplotlib_context_writer/__init__.py
matplotlib_context_writer/implementations.py
matplotlib_context_writer/interface.py
matplotlib_context_writer-0.4.0.dist-info/METADATA
matplotlib_context_writer-0.4.0.dist-info/WHEEL
matplotlib_context_writer-0.4.0.dist-info/RECORD
