Metadata-Version: 2.4
Name: matplotlib-context-writer
Version: 0.4.0
Summary: Plot matplotlib animations flexibly.
Author: Jona Klemenc
Author-email: jona.klemenc@posteo.de
Requires-Python: >3.10.7,<4.0.0
Classifier: Programming Language :: Python :: 3
Classifier: Programming Language :: Python :: 3.11
Classifier: Programming Language :: Python :: 3.12
Classifier: Programming Language :: Python :: 3.13
Classifier: Programming Language :: Python :: 3.14
Requires-Dist: matplotlib (>=3.10.7,<4.0.0)
